amodel/__init__.py
amodel/main.py
amodel/model_manage.py
amodel/model_meta.py
amodel-0.1.1.dist-info/METADATA
amodel-0.1.1.dist-info/WHEEL
amodel-0.1.1.dist-info/entry_points.txt
amodel-0.1.1.dist-info/top_level.txt
amodel-0.1.1.dist-info/RECORD
