Metadata-Version: 2.1
Name: amodel
Version: 0.1.1
Summary: Apollo's model deployment and management tool
Home-page: https://github.com/ApolloAuto/apollo/tree/master/modules/tools/amodel
Author: apollo-team
Author-email: apollo-support@baidu.com
Project-URL: Bug Tracker, https://github.com/ApolloAuto/apollo/issues
Classifier: Programming Language :: Python :: 3
Classifier: License :: OSI Approved :: Apache Software License
Classifier: Operating System :: OS Independent
Requires-Python: >=3.6
